[{"t": 0, "pos": 4, "lap": 1}, {"t": 105147, "pos": 4, "lap": 2}, {"t": 205103, "pos": 4, "lap": 3}, {"t": 304337, "pos": 5, "lap": 4}, {"t": 403972, "pos": 5, "lap": 5}, {"t": 503212, "pos": 5, "lap": 6}, {"t": 602620, "pos": 5, "lap": 7}, {"t": 702288, "pos": 6, "lap": 8}, {"t": 803546, "pos": 4, "lap": 9}, {"t": 905408, "pos": 9, "lap": 10}, {"t": 1011671, "pos": 16, "lap": 11}, {"t": 1128385, "pos": 13, "lap": 12}, {"t": 1227006, "pos": 13, "lap": 13}, {"t": 1325320, "pos": 13, "lap": 14}, {"t": 1425568, "pos": 18, "lap": 15}]