[{"t": 0, "pos": 16, "lap": 1}, {"t": 135647, "pos": 16, "lap": 2}, {"t": 281943, "pos": 16, "lap": 3}, {"t": 419413, "pos": 16, "lap": 4}, {"t": 549240, "pos": 15, "lap": 5}, {"t": 640386, "pos": 15, "lap": 6}, {"t": 730307, "pos": 15, "lap": 7}, {"t": 818835, "pos": 15, "lap": 8}, {"t": 907334, "pos": 15, "lap": 9}, {"t": 995372, "pos": 15, "lap": 10}, {"t": 1083153, "pos": 15, "lap": 11}, {"t": 1172405, "pos": 15, "lap": 12}, {"t": 1259704, "pos": 15, "lap": 13}, {"t": 1347475, "pos": 15, "lap": 14}, {"t": 1435000, "pos": 15, "lap": 15}, {"t": 1522793, "pos": 15, "lap": 16}, {"t": 1610393, "pos": 15, "lap": 17}, {"t": 1697949, "pos": 15, "lap": 18}, {"t": 1785270, "pos": 15, "lap": 19}, {"t": 1872698, "pos": 15, "lap": 20}, {"t": 1960045, "pos": 15, "lap": 21}, {"t": 2047465, "pos": 15, "lap": 22}, {"t": 2134598, "pos": 15, "lap": 23}, {"t": 2221549, "pos": 15, "lap": 24}, {"t": 2308517, "pos": 14, "lap": 25}, {"t": 2395515, "pos": 14, "lap": 26}, {"t": 2482289, "pos": 14, "lap": 27}, {"t": 2568952, "pos": 13, "lap": 28}, {"t": 2655505, "pos": 13, "lap": 29}, {"t": 2741900, "pos": 13, "lap": 30}, {"t": 2828608, "pos": 13, "lap": 31}, {"t": 2914998, "pos": 13, "lap": 32}, {"t": 3001570, "pos": 13, "lap": 33}, {"t": 3087873, "pos": 12, "lap": 34}, {"t": 3175581, "pos": 12, "lap": 35}, {"t": 3297498, "pos": 13, "lap": 36}, {"t": 3440237, "pos": 13, "lap": 37}, {"t": 3558840, "pos": 13, "lap": 38}, {"t": 3705141, "pos": 12, "lap": 39}, {"t": 3834199, "pos": 11, "lap": 40}, {"t": 3948233, "pos": 11, "lap": 41}, {"t": 4082298, "pos": 11, "lap": 42}, {"t": 4218781, "pos": 10, "lap": 43}, {"t": 4306749, "pos": 10, "lap": 44}, {"t": 4393273, "pos": 10, "lap": 45}, {"t": 4479117, "pos": 9, "lap": 46}, {"t": 4564818, "pos": 9, "lap": 47}, {"t": 4650377, "pos": 9, "lap": 48}, {"t": 4736128, "pos": 10, "lap": 49}, {"t": 4823350, "pos": 10, "lap": 50}, {"t": 4910131, "pos": 10, "lap": 51}, {"t": 4996791, "pos": 10, "lap": 52}, {"t": 5084301, "pos": 12, "lap": 53}, {"t": 5174622, "pos": 12, "lap": 54}, {"t": 5262789, "pos": 14, "lap": 55}, {"t": 5355012, "pos": 15, "lap": 56}]