[{"t": 0, "pos": 11, "lap": 1}, {"t": 107362, "pos": 11, "lap": 2}, {"t": 210203, "pos": 11, "lap": 3}, {"t": 344462, "pos": 11, "lap": 4}, {"t": 493966, "pos": 11, "lap": 5}, {"t": 647564, "pos": 11, "lap": 6}, {"t": 750654, "pos": 10, "lap": 7}, {"t": 852082, "pos": 10, "lap": 8}, {"t": 953367, "pos": 10, "lap": 9}, {"t": 1055018, "pos": 10, "lap": 10}, {"t": 1156318, "pos": 10, "lap": 11}, {"t": 1258007, "pos": 10, "lap": 12}, {"t": 1359439, "pos": 10, "lap": 13}, {"t": 1460773, "pos": 10, "lap": 14}, {"t": 1561821, "pos": 10, "lap": 15}, {"t": 1663645, "pos": 10, "lap": 16}, {"t": 1765157, "pos": 10, "lap": 17}, {"t": 1866347, "pos": 8, "lap": 18}, {"t": 1968477, "pos": 7, "lap": 19}, {"t": 2068907, "pos": 7, "lap": 20}, {"t": 2169354, "pos": 7, "lap": 21}, {"t": 2269877, "pos": 7, "lap": 22}, {"t": 2370634, "pos": 7, "lap": 23}, {"t": 2471404, "pos": 7, "lap": 24}, {"t": 2571733, "pos": 7, "lap": 25}, {"t": 2672002, "pos": 7, "lap": 26}, {"t": 2772666, "pos": 6, "lap": 27}, {"t": 2873839, "pos": 12, "lap": 28}, {"t": 2996110, "pos": 12, "lap": 29}, {"t": 3097022, "pos": 12, "lap": 30}, {"t": 3197360, "pos": 11, "lap": 31}, {"t": 3296761, "pos": 11, "lap": 32}, {"t": 3396448, "pos": 11, "lap": 33}, {"t": 3495803, "pos": 11, "lap": 34}, {"t": 3595151, "pos": 11, "lap": 35}, {"t": 3694401, "pos": 11, "lap": 36}, {"t": 3793597, "pos": 10, "lap": 37}, {"t": 3892987, "pos": 10, "lap": 38}, {"t": 3992166, "pos": 9, "lap": 39}, {"t": 4091460, "pos": 8, "lap": 40}, {"t": 4190850, "pos": 7, "lap": 41}, {"t": 4290029, "pos": 7, "lap": 42}, {"t": 4388970, "pos": 7, "lap": 43}, {"t": 4487876, "pos": 7, "lap": 44}, {"t": 4586778, "pos": 8, "lap": 45}, {"t": 4687350, "pos": 8, "lap": 46}, {"t": 4785995, "pos": 8, "lap": 47}, {"t": 4884992, "pos": 8, "lap": 48}, {"t": 4983586, "pos": 8, "lap": 49}, {"t": 5082096, "pos": 8, "lap": 50}, {"t": 5180747, "pos": 8, "lap": 51}, {"t": 5279151, "pos": 8, "lap": 52}, {"t": 5377854, "pos": 8, "lap": 53}, {"t": 5476366, "pos": 8, "lap": 54}, {"t": 5575141, "pos": 8, "lap": 55}, {"t": 5673855, "pos": 8, "lap": 56}]