{"drivers": [{"code": "PIA", "number": "81", "name": "O PIASTRI"}, {"code": "NOR", "number": "4", "name": "L NORRIS"}, {"code": "HAM", "number": "44", "name": "L HAMILTON"}, {"code": "LEC", "number": "16", "name": "C LECLERC"}, {"code": "VER", "number": "1", "name": "M VERSTAPPEN"}, {"code": "SAI", "number": "55", "name": "C SAINZ"}, {"code": "PER", "number": "11", "name": "S PEREZ"}, {"code": "RUS", "number": "63", "name": "G RUSSELL"}, {"code": "TSU", "number": "22", "name": "Y TSUNODA"}, {"code": "STR", "number": "18", "name": "L STROLL"}, {"code": "ALO", "number": "14", "name": "F ALONSO"}, {"code": "RIC", "number": "3", "name": "D RICCIARDO"}, {"code": "HUL", "number": "27", "name": "N HULKENBERG"}, {"code": "ALB", "number": "23", "name": "A ALBON"}, {"code": "MAG", "number": "20", "name": "K MAGNUSSEN"}, {"code": "BOT", "number": "77", "name": "V BOTTAS"}, {"code": "SAR", "number": "2", "name": "L SARGEANT"}, {"code": "OCO", "number": "31", "name": "E OCON"}, {"code": "ZHO", "number": "24", "name": "G ZHOU"}, {"code": "GAS", "number": "10", "name": "P GASLY"}]}